msg_decoder.sv
/* verilator lint_off IMPORTSTAR */
import itch_lite_pkg::*;
/* verilator lint_on IMPORTSTAR */

module msg_decoder (
    input  logic        clk,
    input  logic        rst_n,

    // AXI-Stream Slave
    input  logic [63:0] s_axis_tdata,
    input  logic        s_axis_tvalid,
    input  logic [7:0]  s_axis_tkeep,
    input  logic        s_axis_tlast,
    output logic        s_axis_tready,

    // Control input and outputs
    input  logic        m_axis_tready,  // downstream readiness
    output logic        msg_start,
    output logic        header_valid,
    output logic        msg_done,
    output logic        framing_error,

    // Decoded event output (plain logic for Yosys compatibility)
    output logic [287:0] order_event_raw
);

    // Internal typed signal; assign to flat output at boundary
    order_event_t order_event;
    assign order_event_raw = order_event;

    // ------------------------------------------------------------------------
    // Internal Registers
    // ------------------------------------------------------------------------
    logic [7:0]  byte_cnt;
    logic [63:0] prev_tdata;

    // ------------------------------------------------------------------------
    // AXI Helpers & 128-bit Sliding Window
    // ------------------------------------------------------------------------
    assign s_axis_tready = m_axis_tready && rst_n;

    logic [3:0] bytes_in_word;
    assign bytes_in_word = $countones(s_axis_tkeep);

    logic [8:0] total_bytes;
    assign total_bytes = byte_cnt + {5'b0, bytes_in_word};

    // Window: prev_tdata in [63:0], incoming tdata in [127:64]
    // byte 0 of the current word is at window[(byte_cnt_offset + 8)*8 +: 8]
    logic [127:0] window;
    assign window = {s_axis_tdata, prev_tdata};

    // ------------------------------------------------------------------------
    // Combinational Processes
    // ------------------------------------------------------------------------
    // Peek ahead at wire on first word, otherwise use latched msg_type
    msg_type_e active_msg_type;
    always_comb begin
        if (byte_cnt == 0 && total_bytes >= 1)
            active_msg_type = msg_type_e'(window[71:64]);
        else
            active_msg_type = order_event.msg_type;
    end
    
    // Message length lookup
    logic [7:0]  current_msg_len;
    always_comb begin
        case (active_msg_type)
            MSG_ADD:     current_msg_len = ADD_LEN;
            MSG_CANCEL:  current_msg_len = CANCEL_LEN;
            MSG_EXECUTE: current_msg_len = EXECUTE_LEN;
            default:     current_msg_len = '0;
        endcase
    end

    // Update for byte_cnt
    logic [8:0]  byte_cnt_next;
    assign byte_cnt_next = total_bytes - {1'b0, current_msg_len};

    // ------------------------------------------------------------------------
    // Error Handling
    // ------------------------------------------------------------------------
    logic framing_error_now;
    assign framing_error_now = s_axis_tvalid && s_axis_tready && s_axis_tlast 
                                && (total_bytes < {1'b0, current_msg_len});

    // ------------------------------------------------------------------------
    // Sequential Process
    // ------------------------------------------------------------------------
    always_ff @(posedge clk or negedge rst_n) begin
        if (!rst_n) begin
            byte_cnt      <= '0;
            prev_tdata    <= '0;
            msg_start     <= '0;
            header_valid  <= '0;
            msg_done      <= '0;
            framing_error <= '0;
            order_event   <= '0;
        end else begin
            msg_start     <= '0;
            header_valid  <= '0;
            msg_done      <= '0;
            framing_error <= '0;
            if (msg_done) order_event <= '0;

            if (s_axis_tvalid && s_axis_tready) begin
                prev_tdata <= s_axis_tdata;

                // ------------------------------------------------------------
                // 1. Start pulse on first byte of new message
                // ------------------------------------------------------------
                if (byte_cnt == 0 && total_bytes >= 1)
                    msg_start <= 1'b1;

                // ------------------------------------------------------------
                // 2. Field extraction from sliding window
                //    Formula: window[((offset - byte_cnt + 8) * 8) +: width]
                //    The +8 accounts for prev_tdata occupying window[63:0];
                //    s_axis_tdata occupies window[127:64], so byte 0 of the
                //    current incoming word is window[64 +: 8] = tdata[7:0].
                // ------------------------------------------------------------

                // msg_type (offset 0, 8 bits)
                if (byte_cnt < 1 && total_bytes >= 1)
                    order_event.msg_type <= msg_type_e'(window[((0 - byte_cnt + 8) * 8) +: 8]);

                // stock_locate (offset 1, 16 bits)
                if (byte_cnt < 3 && total_bytes >= 3)
                    order_event.stock_locate <= bswap16(window[((1 - byte_cnt + 8) * 8) +: 16]);

                // tracking_number (offset 3, 16 bits)
                if (byte_cnt < 5 && total_bytes >= 5)
                    order_event.tracking_number <= bswap16(window[((3 - byte_cnt + 8) * 8) +: 16]);

                // timestamp (offset 5, 48 bits)
                if (byte_cnt < 11 && total_bytes >= 11)
                    order_event.timestamp <= bswap48(window[((5 - byte_cnt + 8) * 8) +: 48]);

                // order_ref (offset 11, 64 bits) — header complete when this lands
                if (byte_cnt < 19 && total_bytes >= 19) begin
                    order_event.order_ref <= bswap64(window[((11 - byte_cnt + 8) * 8) +: 64]);
                    header_valid          <= 1'b1;
                end

                // ------------------------------------------------------------
                // 3. Type-specific payload fields
                // ------------------------------------------------------------
                unique case (active_msg_type)
                    MSG_ADD: begin
                        // side (offset 19, 8 bits) — no swap needed for 1-byte field
                        if (byte_cnt < 20 && total_bytes >= 20)
                            order_event.payload.add.side <= side_e'(window[((19 - byte_cnt + 8) * 8) +: 8]);
                        // shares (offset 20, 32 bits)
                        if (byte_cnt < 24 && total_bytes >= 24)
                            order_event.payload.add.shares <= bswap32(window[((20 - byte_cnt + 8) * 8) +: 32]);
                        // symbol (offset 24, 64 bits) — skipped, not decoded
                        // price (offset 32, 32 bits)
                        if (byte_cnt < 36 && total_bytes >= 36)
                            order_event.payload.add.price <= bswap32(window[((32 - byte_cnt + 8) * 8) +: 32]);
                    end

                    MSG_CANCEL: begin
                        // cancelled_shares (offset 19, 32 bits)
                        if (byte_cnt < 23 && total_bytes >= 23)
                            order_event.payload.cancel.shares <= bswap32(window[((19 - byte_cnt + 8) * 8) +: 32]);
                    end

                    MSG_EXECUTE: begin
                        // executed_shares (offset 19, 32 bits)
                        if (byte_cnt < 23 && total_bytes >= 23)
                            order_event.payload.execute.shares <= bswap32(window[((19 - byte_cnt + 8) * 8) +: 32]);
                        // match_number (offset 23, 64 bits)
                        if (byte_cnt < 31 && total_bytes >= 31)
                            order_event.payload.execute.match <= bswap64(window[((23 - byte_cnt + 8) * 8) +: 64]);
                    end

                    default: ;
                endcase

                // ------------------------------------------------------------
                // 4. Message completion & packet boundary recovery
                // ------------------------------------------------------------
                if (current_msg_len != '0) begin
                    if (total_bytes >= {1'b0, current_msg_len}) begin
                        msg_done <= 1'b1;
                        // If tlast coincides with message boundary, reset cleanly;
                        // otherwise carry leftover bytes into the next cycle
                        byte_cnt <= s_axis_tlast ? '0 : byte_cnt_next[7:0];
                    end else begin
                        if (s_axis_tlast) begin
                            // Packet ended before message was complete — framing error
                            framing_error <= 1'b1;
                            byte_cnt      <= '0;
                        end else begin
                            byte_cnt <= total_bytes;
                        end
                    end
                end else if (!framing_error_now) begin
                    // Unknown message type — pulse done and reset
                    msg_done <= 1'b1;
                    byte_cnt <= '0;
                end
            end
        end
    end

    // ------------------------------------------------------------------------
    // SVA Assertions (formal verification only)
    // ------------------------------------------------------------------------
`ifdef FORMAL
    property p_byte_cnt_bounded;
        @(posedge clk) disable iff (!rst_n)
        (byte_cnt > 0) |-> (byte_cnt < current_msg_len);
    endproperty
    assert property (p_byte_cnt_bounded) else $error("byte_cnt exceeded valid message length");

    property p_msg_done_one_cycle;
        @(posedge clk) disable iff (!rst_n)
        msg_done |=> !msg_done;
    endproperty
    assert property (p_msg_done_one_cycle) else $error("msg_done held high 2+ cycles");

    property p_cnt_resets_after_done;
        @(posedge clk) disable iff (!rst_n)
        (msg_done && s_axis_tlast) |=> (byte_cnt == 0);
    endproperty
    assert property (p_cnt_resets_after_done) else $error("byte_cnt did not reset after msg_done+tlast");

    property p_legal_msg_type;
        @(posedge clk) disable iff (!rst_n)
        (byte_cnt > 0) |-> (order_event.msg_type == MSG_ADD ||
                            order_event.msg_type == MSG_CANCEL ||
                            order_event.msg_type == MSG_EXECUTE);
    endproperty
    assert property (p_legal_msg_type) else $error("illegal msg_type mid-message");
`endif

endmodule

tb/msg_decoder_tb.sv
/* verilator lint_off IMPORTSTAR */
import itch_lite_pkg::*; //[cite: 1]
/* verilator lint_on IMPORTSTAR */

module msg_decoder_tb;

    timeunit 1ns; timeprecision 1ps;

    // Clock and reset
    logic clk = 0;
    always #5 clk = ~clk;   // 10ns period = 100MHz

    logic rst_n;

    // DUT AXI-Stream Slave interface (matching msg_decoder.sv ports)[cite: 2]
    logic [63:0] s_axis_tdata;
    logic        s_axis_tvalid;
    logic [7:0]  s_axis_tkeep;
    logic        s_axis_tlast;
    logic        s_axis_tready;

    // DUT Control & Status interface[cite: 2]
    logic        m_axis_tready;
    logic        msg_start;
    logic        header_valid;
    logic        msg_done;
    logic        framing_error;
    logic [287:0] order_event_raw; //[cite: 2]

    // Unpack raw vector to structured type defined in itch_lite_pkg[cite: 1, 2]
    order_event_t order_event;
    assign order_event = order_event_t'(order_event_raw);

    msg_decoder dut (.*); //[cite: 2]

    // Waveform dump
    initial begin
        $dumpfile("dump_directed.vcd");
        $dumpvars(0, msg_decoder_tb);
    end

    // Module-scope static queue to prevent Icarus Verilog automatic argument crashes[cite: 3]
    logic [7:0] tx_queue[$];

    // ---------------------------------------------------------------------
    // 64-Bit AXI-Stream Driver Task
    // ---------------------------------------------------------------------
    task automatic send_message(input logic set_tlast = 1'b1);
        while (tx_queue.size() > 0) begin
            logic [63:0] word_data = '0;
            logic [7:0]  word_keep = '0;
            int n = (tx_queue.size() >= 8) ? 8 : tx_queue.size();

            for (int i = 0; i < n; i++) begin
                word_data[i*8 +: 8] = tx_queue.pop_front();
                word_keep[i]        = 1'b1;
            end

            s_axis_tdata  <= word_data;
            s_axis_tkeep  <= word_keep;
            s_axis_tvalid <= 1'b1;
            s_axis_tlast  <= (tx_queue.size() == 0 && set_tlast) ? 1'b1 : 1'b0;

            do begin
                @(posedge clk);
            end while (!s_axis_tready); //[cite: 2]
        end

        s_axis_tvalid <= 1'b0;
        s_axis_tlast  <= 1'b0;
        s_axis_tkeep  <= '0;
        s_axis_tdata  <= '0;
    endtask

    // ---------------------------------------------------------------------
    // Synchronization & Checking Helpers (with NBA race avoidance)
    // ---------------------------------------------------------------------
    int errors = 0;
    task automatic wait_and_check_done();
        #1; // Step past NBA region
        if (!msg_done) begin
            int timeout = 20;
            while (!msg_done && timeout > 0) begin
                @(posedge clk);
                #1;
                timeout--;
            end
        end
        if (!msg_done) begin
            $display("FAIL: msg_done did not pulse within timeout!");
            errors++;
        end
    endtask

    task automatic check(string field_name, logic [63:0] actual, logic [63:0] expected);
        if (actual !== expected) begin
            $display("FAIL: %s = %0d, expected %0d", field_name, actual, expected);
            errors++;
        end else begin
            $display("PASS: %s = %0d", field_name, actual);
        end
    endtask

    // Standard ITCH Directed Test Vectors[cite: 4]
    logic [7:0] add_msg [0:35] = '{
        8'h41,                                                  // msg_type 'A'[cite: 1, 4]
        8'h00, 8'h01,                                           // stock_locate = 1[cite: 4]
        8'h00, 8'h01,                                           // tracking_number = 1[cite: 4]
        8'h00, 8'h00, 8'h00, 8'h00, 8'h00, 8'h64,               // timestamp = 100[cite: 4]
        8'h00, 8'h00, 8'h00, 8'h00, 8'h00, 8'h00, 8'h00, 8'h01, // order_ref = 1[cite: 4]
        8'h42,                                                  // side 'B' (buy)[cite: 1, 4]
        8'h00, 8'h00, 8'h00, 8'h64,                             // shares = 100[cite: 4]
        8'h41, 8'h41, 8'h50, 8'h4C, 8'h20, 8'h20, 8'h20, 8'h20, // symbol "AAPL    "[cite: 4]
        8'h00, 8'h07, 8'hA1, 8'h20                              // price = 500000[cite: 4]
    };

    logic [7:0] cancel_msg [0:22] = '{
        8'h58,                                                  // msg_type 'X'[cite: 1, 4]
        8'h00, 8'h01,                                           // stock_locate = 1[cite: 4]             
        8'h00, 8'h01,                                           // tracking_number = 1[cite: 4]
        8'h00, 8'h00, 8'h00, 8'h00, 8'h00, 8'hC8,               // timestamp = 200[cite: 4]
        8'h00, 8'h00, 8'h00, 8'h00, 8'h00, 8'h00, 8'h00, 8'h01, // order_ref = 1[cite: 4]
        8'h00, 8'h00, 8'h00, 8'h1E                              // cancelled_shares = 30[cite: 4]
    };

    logic [7:0] execute_msg [0:30] = '{
        8'h45,                                                  // msg_type 'E'[cite: 1, 4]
        8'h00, 8'h01,                                           // stock_locate = 1[cite: 4]
        8'h00, 8'h01,                                           // tracking_number = 1[cite: 4]
        8'h00, 8'h00, 8'h00, 8'h00, 8'h01, 8'h2C,               // timestamp = 300[cite: 4]
        8'h00, 8'h00, 8'h00, 8'h00, 8'h00, 8'h00, 8'h00, 8'h01, // order_ref = 1[cite: 4]
        8'h00, 8'h00, 8'h00, 8'h28,                             // executed_shares = 40[cite: 4]
        8'h00, 8'h00, 8'h00, 8'h00, 8'h00, 8'h00, 8'h03, 8'hE8  // match_number = 1000[cite: 4]
    };

    initial begin
        rst_n         <= 0;
        s_axis_tvalid <= 0;
        s_axis_tdata  <= '0;
        s_axis_tkeep  <= '0;
        s_axis_tlast  <= 0;
        m_axis_tready <= 1;

        repeat (3) @(posedge clk);
        rst_n <= 1;
        @(posedge clk);

        // ---------------- Add Order ----------------
        $display("\n--- Sending Add Order ---");
        tx_queue = {};
        for (int i = 0; i < 36; i++) tx_queue.push_back(add_msg[i]);
        send_message(1'b1);
        wait_and_check_done();
        
        check("msg_type",        order_event.msg_type,          MSG_ADD); //[cite: 1]
        check("stock_locate",    order_event.stock_locate,      1);
        check("tracking_number", order_event.tracking_number,   1);
        check("timestamp",       order_event.timestamp,         100);
        check("order_ref",       order_event.order_ref,         1);
        check("side",            order_event.payload.add.side,   SIDE_BUY); //[cite: 1]
        check("shares",          order_event.payload.add.shares, 100);
        check("price",           order_event.payload.add.price,  500000);
        @(posedge clk);

        // ---------------- Order Cancel ----------------
        $display("\n--- Sending Cancel Order ---");
        tx_queue = {};
        for (int i = 0; i < 23; i++) tx_queue.push_back(cancel_msg[i]);
        send_message(1'b1);
        wait_and_check_done();
        
        check("msg_type",         order_event.msg_type,              MSG_CANCEL); //[cite: 1]
        check("timestamp",        order_event.timestamp,             200);
        check("order_ref",        order_event.order_ref,             1);
        check("cancelled_shares", order_event.payload.cancel.shares, 30);
        @(posedge clk);

        // ---------------- Order Executed ----------------
        $display("\n--- Sending Execute Order ---");
        tx_queue = {};
        for (int i = 0; i < 31; i++) tx_queue.push_back(execute_msg[i]);
        send_message(1'b1);
        wait_and_check_done();
        
        check("msg_type",        order_event.msg_type,               MSG_EXECUTE); //[cite: 1]
        check("timestamp",       order_event.timestamp,              300);
        check("order_ref",       order_event.order_ref,              1);
        check("executed_shares", order_event.payload.execute.shares, 40);
        check("match_number",    order_event.payload.execute.match,  1000);
        @(posedge clk);

        $finish;
    end

    final begin
        if (errors == 0) $display("\n=== ALL DIRECTED TESTS PASSED ===");
        else             $display("\n=== %0d CHECK(S) FAILED ===", errors);
    end

endmodule

dump_directed.vcd
$date
	Sun Jul 26 18:29:23 2026
$end
$version
	Icarus Verilog
$end
$timescale
	1ps
$end
$scope module msg_decoder_tb $end
$var wire 288 ! order_event [287:0] $end
$var wire 1 " s_axis_tready $end
$var wire 288 # order_event_raw [287:0] $end
$var wire 1 $ msg_start $end
$var wire 1 % msg_done $end
$var wire 1 & header_valid $end
$var wire 1 ' framing_error $end
$var reg 1 ( clk $end
$var reg 1 ) m_axis_tready $end
$var reg 1 * rst_n $end
$var reg 64 + s_axis_tdata [63:0] $end
$var reg 8 , s_axis_tkeep [7:0] $end
$var reg 1 - s_axis_tlast $end
$var reg 1 . s_axis_tvalid $end
$var integer 32 / errors [31:0] $end
$scope module dut $end
$var wire 1 ( clk $end
$var wire 1 0 framing_error_now $end
$var wire 1 ) m_axis_tready $end
$var wire 288 1 order_event_raw [287:0] $end
$var wire 1 * rst_n $end
$var wire 64 2 s_axis_tdata [63:0] $end
$var wire 8 3 s_axis_tkeep [7:0] $end
$var wire 1 - s_axis_tlast $end
$var wire 1 " s_axis_tready $end
$var wire 1 . s_axis_tvalid $end
$var wire 128 4 window [127:0] $end
$var wire 9 5 total_bytes [8:0] $end
$var wire 4 6 bytes_in_word [3:0] $end
$var wire 9 7 byte_cnt_next [8:0] $end
$var reg 8 8 active_msg_type [7:0] $end
$var reg 8 9 byte_cnt [7:0] $end
$var reg 8 : current_msg_len [7:0] $end
$var reg 1 ' framing_error $end
$var reg 1 & header_valid $end
$var reg 1 % msg_done $end
$var reg 1 $ msg_start $end
$var reg 288 ; order_event [287:0] $end
$var reg 64 < prev_tdata [63:0] $end
$upscope $end
$scope begin $ivl_for_loop1 $end
$var integer 32 = i [31:0] $end
$upscope $end
$scope begin $ivl_for_loop2 $end
$var integer 32 > i [31:0] $end
$upscope $end
$scope begin $ivl_for_loop3 $end
$var integer 32 ? i [31:0] $end
$upscope $end
$scope task check $end
$upscope $end
$scope task send_message $end
$scope begin $unm_blk_18 $end
$scope begin $ivl_for_loop0 $end
$upscope $end
$upscope $end
$upscope $end
$scope task wait_and_check_done $end
$scope begin $unm_blk_21 $end
$upscope $end
$upscope $end
$upscope $end
$enddefinitions $end
$comment Show the parameter values. $end
$dumpall
$end
#0
$dumpvars
b0 ?
b0 >
b0 =
b0 <
b0 ;
b0 :
b0 9
b0 8
b0 7
b0 6
b0 5
b0 4
b0 3
b0 2
b0 1
00
b0 /
0.
0-
b0 ,
b0 +
0*
1)
0(
0'
0&
0%
0$
b0 #
0"
b0 !
$end
#5000
1(
#10000
0(
#15000
1(
#20000
0(
#25000
1"
1*
1(
#30000
0(
#35000
b100100 :
b1000001 8
b111100100 7
b1000 5
b1000 6
b1000000000000000100000000010000010000000000000000000000000000000000000000000000000000000000000000 4
1.
b11111111 ,
b11111111 3
b100000000000000010000000001000001 +
b100000000000000010000000001000001 2
b100100 =
1(
#40000
0(
#45000
b111101100 7
b10000 5
b110010000000000000000000000000000000000000000000000000100000000000000010000000001000001 4
b1000 9
b10000010000000000000001000000000000000100000000000000000000000000000000000000000000000000000000000000000000000000000000000000000000000000000000000000000000000000000000000000000000000000000000000000000000000000000000000000000000000000000000000000000000000000000000000000000000000000000000 !
b10000010000000000000001000000000000000100000000000000000000000000000000000000000000000000000000000000000000000000000000000000000000000000000000000000000000000000000000000000000000000000000000000000000000000000000000000000000000000000000000000000000000000000000000000000000000000000000000 #
b10000010000000000000001000000000000000100000000000000000000000000000000000000000000000000000000000000000000000000000000000000000000000000000000000000000000000000000000000000000000000000000000000000000000000000000000000000000000000000000000000000000000000000000000000000000000000000000000 1
b10000010000000000000001000000000000000100000000000000000000000000000000000000000000000000000000000000000000000000000000000000000000000000000000000000000000000000000000000000000000000000000000000000000000000000000000000000000000000000000000000000000000000000000000000000000000000000000000 ;
1$
b100000000000000010000000001000001 <
b11001000000000000000000 +
b11001000000000000000000 2
1(
#50000
0(
#55000
b111110100 7
b11000 5
b1100100000000000000000000000000010000100000000100000000000000000000000000000000000000000000000000000000011001000000000000000000 4
b10000 9
b10000010000000000000001000000000000000100000000000000000000000000000000000000000110010000000000000000000000000000000000000000000000000000000000000000000000000000000000000000000000000000000000000000000000000000000000000000000000000000000000000000000000000000000000000000000000000000000000 !
b10000010000000000000001000000000000000100000000000000000000000000000000000000000110010000000000000000000000000000000000000000000000000000000000000000000000000000000000000000000000000000000000000000000000000000000000000000000000000000000000000000000000000000000000000000000000000000000000 #
b10000010000000000000001000000000000000100000000000000000000000000000000000000000110010000000000000000000000000000000000000000000000000000000000000000000000000000000000000000000000000000000000000000000000000000000000000000000000000000000000000000000000000000000000000000000000000000000000 1
b10000010000000000000001000000000000000100000000000000000000000000000000000000000110010000000000000000000000000000000000000000000000000000000000000000000000000000000000000000000000000000000000000000000000000000000000000000000000000000000000000000000000000000000000000000000000000000000000 ;
b11001000000000000000000 <
0$
b110010000000000000000000000000001000010000000010000000000000000 +
b110010000000000000000000000000001000010000000010000000000000000 2
1(
#60000
0(
#65000
b111111100 7
b100000 5
b100000001000000010000000100000010011000101000001000001010000010110010000000000000000000000000001000010000000010000000000000000 4
b11000 9
1&
b10000010000000000000001000000000000000100000000000000000000000000000000000000000110010000000000000000000000000000000000000000000000000000000000000000010100001000000000000000000000000001100100000000000000000000000000000000000000000000000000000000000000000000000000000000000000000000000000 !
b10000010000000000000001000000000000000100000000000000000000000000000000000000000110010000000000000000000000000000000000000000000000000000000000000000010100001000000000000000000000000001100100000000000000000000000000000000000000000000000000000000000000000000000000000000000000000000000000 #
b10000010000000000000001000000000000000100000000000000000000000000000000000000000110010000000000000000000000000000000000000000000000000000000000000000010100001000000000000000000000000001100100000000000000000000000000000000000000000000000000000000000000000000000000000000000000000000000000 1
b10000010000000000000001000000000000000100000000000000000000000000000000000000000110010000000000000000000000000000000000000000000000000000000000000000010100001000000000000000000000000001100100000000000000000000000000000000000000000000000000000000000000000000000000000000000000000000000000 ;
b110010000000000000000000000000001000010000000010000000000000000 <
b10000000100000001000000010000001001100010100000100000101000001 +
b10000000100000001000000010000001001100010100000100000101000001 2
1(
#70000
0(
#75000
b100 6
b0 7
b100100 5
b1000001010000100000111000000000010000000100000001000000010000001001100010100000100000101000001 4
b100000 9
b10000000100000001000000010000001001100010100000100000101000001 <
0&
1-
b1111 ,
b1111 3
b100000101000010000011100000000 +
b100000101000010000011100000000 2
1(
#80000
0(
#85000
b100100 :
b0 6
b111011100 7
b0 5
b1000001 8
b100000101000010000011100000000 4
b0 9
1%
b10000010000000000000001000000000000000100000000000000000000000000000000000000000110010000000000000000000000000000000000000000000000000000000000000000010100001000000000000000000000000001100100000000000000011110100001001000000000000000000000000000000000000000000000000000000000000000000000 !
b10000010000000000000001000000000000000100000000000000000000000000000000000000000110010000000000000000000000000000000000000000000000000000000000000000010100001000000000000000000000000001100100000000000000011110100001001000000000000000000000000000000000000000000000000000000000000000000000 #
b10000010000000000000001000000000000000100000000000000000000000000000000000000000110010000000000000000000000000000000000000000000000000000000000000000010100001000000000000000000000000001100100000000000000011110100001001000000000000000000000000000000000000000000000000000000000000000000000 1
b10000010000000000000001000000000000000100000000000000000000000000000000000000000110010000000000000000000000000000000000000000000000000000000000000000010100001000000000000000000000000001100100000000000000011110100001001000000000000000000000000000000000000000000000000000000000000000000000 ;
b100000101000010000011100000000 <
b0 +
b0 2
b0 ,
b0 3
0-
0.
1(
#90000
0(
#95000
b111110001 7
b1000 5
b10111 :
b1000 6
b1011000 8
b1000000000000000100000000010110000000000000000000000000000000000000100000101000010000011100000000 4
b0 !
b0 #
b0 1
b0 ;
0%
1.
b11111111 ,
b11111111 3
b100000000000000010000000001011000 +
b100000000000000010000000001011000 2
b10111 >
1(
#100000
0(
#105000
b111111001 7
b10000 5
b1100100000000000000000000000000000000000000000000000000100000000000000010000000001011000 4
b1000 9
b10110000000000000000001000000000000000100000000000000000000000000000000000000000000000000000000000000000000000000000000000000000000000000000000000000000000000000000000000000000000000000000000000000000000000000000000000000000000000000000000000000000000000000000000000000000000000000000000 !
b10110000000000000000001000000000000000100000000000000000000000000000000000000000000000000000000000000000000000000000000000000000000000000000000000000000000000000000000000000000000000000000000000000000000000000000000000000000000000000000000000000000000000000000000000000000000000000000000 #
b10110000000000000000001000000000000000100000000000000000000000000000000000000000000000000000000000000000000000000000000000000000000000000000000000000000000000000000000000000000000000000000000000000000000000000000000000000000000000000000000000000000000000000000000000000000000000000000000 1
b10110000000000000000001000000000000000100000000000000000000000000000000000000000000000000000000000000000000000000000000000000000000000000000000000000000000000000000000000000000000000000000000000000000000000000000000000000000000000000000000000000000000000000000000000000000000000000000000 ;
1$
b100000000000000010000000001011000 <
b110010000000000000000000 +
b110010000000000000000000 2
1(
#110000
0(
#115000
b111 6
b0 7
b10111 5
b111100000000000000000000000000000000100000000000000000000000000000000000000000000000000000000110010000000000000000000 4
b10000 9
b10110000000000000000001000000000000000100000000000000000000000000000000000000001100100000000000000000000000000000000000000000000000000000000000000000000000000000000000000000000000000000000000000000000000000000000000000000000000000000000000000000000000000000000000000000000000000000000000 !
b10110000000000000000001000000000000000100000000000000000000000000000000000000001100100000000000000000000000000000000000000000000000000000000000000000000000000000000000000000000000000000000000000000000000000000000000000000000000000000000000000000000000000000000000000000000000000000000000 #
b10110000000000000000001000000000000000100000000000000000000000000000000000000001100100000000000000000000000000000000000000000000000000000000000000000000000000000000000000000000000000000000000000000000000000000000000000000000000000000000000000000000000000000000000000000000000000000000000 1
b10110000000000000000001000000000000000100000000000000000000000000000000000000001100100000000000000000000000000000000000000000000000000000000000000000000000000000000000000000000000000000000000000000000000000000000000000000000000000000000000000000000000000000000000000000000000000000000000 ;
b110010000000000000000000 <
0$
1-
b1111111 ,
b1111111 3
b11110000000000000000000000000000000010000000000000000 +
b11110000000000000000000000000000000010000000000000000 2
1(
#120000
0(
#125000
b10111 :
b0 6
b111101001 7
b0 5
b1011000 8
b11110000000000000000000000000000000010000000000000000 4
b0 9
1%
1&
b10110000000000000000001000000000000000100000000000000000000000000000000000000001100100000000000000000000000000000000000000000000000000000000000000000010000000000000000000000000001111000000000000000000000000000000000000000000000000000000000000000000000000000000000000000000000000000000000 !
b10110000000000000000001000000000000000100000000000000000000000000000000000000001100100000000000000000000000000000000000000000000000000000000000000000010000000000000000000000000001111000000000000000000000000000000000000000000000000000000000000000000000000000000000000000000000000000000000 #
b10110000000000000000001000000000000000100000000000000000000000000000000000000001100100000000000000000000000000000000000000000000000000000000000000000010000000000000000000000000001111000000000000000000000000000000000000000000000000000000000000000000000000000000000000000000000000000000000 1
b10110000000000000000001000000000000000100000000000000000000000000000000000000001100100000000000000000000000000000000000000000000000000000000000000000010000000000000000000000000001111000000000000000000000000000000000000000000000000000000000000000000000000000000000000000000000000000000000 ;
b11110000000000000000000000000000000010000000000000000 <
b0 +
b0 2
b0 ,
b0 3
0-
0.
1(
#130000
0(
#135000
b111101001 7
b1000 5
b11111 :
b1000 6
b1000101 8
b1000000000000000100000000010001010000000000011110000000000000000000000000000000010000000000000000 4
b0 !
b0 #
b0 1
b0 ;
0%
0&
1.
b11111111 ,
b11111111 3
b100000000000000010000000001000101 +
b100000000000000010000000001000101 2
b11111 ?
1(
#140000
0(
#145000
b111110001 7
b10000 5
b10110000000001000000000000000000000000000000000000000100000000000000010000000001000101 4
b1000 9
b10001010000000000000001000000000000000100000000000000000000000000000000000000000000000000000000000000000000000000000000000000000000000000000000000000000000000000000000000000000000000000000000000000000000000000000000000000000000000000000000000000000000000000000000000000000000000000000000 !
b10001010000000000000001000000000000000100000000000000000000000000000000000000000000000000000000000000000000000000000000000000000000000000000000000000000000000000000000000000000000000000000000000000000000000000000000000000000000000000000000000000000000000000000000000000000000000000000000 #
b10001010000000000000001000000000000000100000000000000000000000000000000000000000000000000000000000000000000000000000000000000000000000000000000000000000000000000000000000000000000000000000000000000000000000000000000000000000000000000000000000000000000000000000000000000000000000000000000 1
b10001010000000000000001000000000000000100000000000000000000000000000000000000000000000000000000000000000000000000000000000000000000000000000000000000000000000000000000000000000000000000000000000000000000000000000000000000000000000000000000000000000000000000000000000000000000000000000000 ;
1$
b100000000000000010000000001000101 <
b1011000000000100000000 +
b1011000000000100000000 2
1(
#150000
0(
#155000
b111111001 7
b11000 5
b1010000000000000000000000000000000000100000000000000000000000000000000000000000000000000000000001011000000000100000000 4
b10000 9
b10001010000000000000001000000000000000100000000000000000000000000000000000000010010110000000000000000000000000000000000000000000000000000000000000000000000000000000000000000000000000000000000000000000000000000000000000000000000000000000000000000000000000000000000000000000000000000000000 !
b10001010000000000000001000000000000000100000000000000000000000000000000000000010010110000000000000000000000000000000000000000000000000000000000000000000000000000000000000000000000000000000000000000000000000000000000000000000000000000000000000000000000000000000000000000000000000000000000 #
b10001010000000000000001000000000000000100000000000000000000000000000000000000010010110000000000000000000000000000000000000000000000000000000000000000000000000000000000000000000000000000000000000000000000000000000000000000000000000000000000000000000000000000000000000000000000000000000000 1
b10001010000000000000001000000000000000100000000000000000000000000000000000000010010110000000000000000000000000000000000000000000000000000000000000000000000000000000000000000000000000000000000000000000000000000000000000000000000000000000000000000000000000000000000000000000000000000000000 ;
b1011000000000100000000 <
0$
b101000000000000000000000000000000000010000000000000000 +
b101000000000000000000000000000000000010000000000000000 2
1(
#160000
0(
#165000
b111 6
b0 7
b11111 5
b111010000000001100000000000000000000000000000000000000000000000000101000000000000000000000000000000000010000000000000000 4
b11000 9
1&
b10001010000000000000001000000000000000100000000000000000000000000000000000000010010110000000000000000000000000000000000000000000000000000000000000000010000000000000000000000000010100000000000000000000000000000000000000000000000000000000000000000000000000000000000000000000000000000000000 !
b10001010000000000000001000000000000000100000000000000000000000000000000000000010010110000000000000000000000000000000000000000000000000000000000000000010000000000000000000000000010100000000000000000000000000000000000000000000000000000000000000000000000000000000000000000000000000000000000 #
b10001010000000000000001000000000000000100000000000000000000000000000000000000010010110000000000000000000000000000000000000000000000000000000000000000010000000000000000000000000010100000000000000000000000000000000000000000000000000000000000000000000000000000000000000000000000000000000000 1
b10001010000000000000001000000000000000100000000000000000000000000000000000000010010110000000000000000000000000000000000000000000000000000000000000000010000000000000000000000000010100000000000000000000000000000000000000000000000000000000000000000000000000000000000000000000000000000000000 ;
b101000000000000000000000000000000000010000000000000000 <
1-
b1111111 ,
b1111111 3
b11101000000000110000000000000000000000000000000000000000 +
b11101000000000110000000000000000000000000000000000000000 2
1(
#170000
0(
