msg_decoder.sv
/* verilator lint_off IMPORTSTAR */
import itch_lite_pkg::*;
/* verilator lint_on IMPORTSTAR */

module msg_decoder (
    input  logic        clk,
    input  logic        rst_n,

    // AXI-Stream Slave
    input  logic [63:0] s_axis_tdata,
    input  logic        s_axis_tvalid,
    input  logic [7:0]  s_axis_tkeep,
    input  logic        s_axis_tlast,
    output logic        s_axis_tready,

    // Control input and outputs
    input  logic        m_axis_tready,  // downstream readiness
    output logic        msg_start,
    output logic        header_valid,
    output logic        msg_done,
    output logic        framing_error,

    // Decoded event output (plain logic for Yosys compatibility)
    output logic [287:0] order_event_raw
);

    // Internal typed signal; assign to flat output at boundary
    order_event_t order_event;
    assign order_event_raw = order_event;

    // ------------------------------------------------------------------------
    // Internal Registers
    // ------------------------------------------------------------------------
    logic [7:0]  byte_cnt;
    logic [63:0] prev_tdata;

    // ------------------------------------------------------------------------
    // AXI Helpers & 128-bit Sliding Window
    // ------------------------------------------------------------------------
    assign s_axis_tready = m_axis_tready && rst_n;

    logic [3:0] bytes_in_word;
    assign bytes_in_word = $countones(s_axis_tkeep);

    logic [8:0] total_bytes;
    assign total_bytes = byte_cnt + {5'b0, bytes_in_word};

    // Window: prev_tdata in [63:0], incoming tdata in [127:64]
    // byte 0 of the current word is at window[(byte_cnt_offset + 8)*8 +: 8]
    logic [127:0] window;
    assign window = {s_axis_tdata, prev_tdata};

    // ------------------------------------------------------------------------
    // Combinational Processes
    // ------------------------------------------------------------------------
    // Peek ahead at wire on first word, otherwise use latched msg_type
    msg_type_e active_msg_type;
    always_comb begin
        if (byte_cnt == 0 && total_bytes >= 1)
            active_msg_type = msg_type_e'(window[71:64]);
        else
            active_msg_type = order_event.msg_type;
    end
    
    // Message length lookup
    logic [7:0]  current_msg_len;
    always_comb begin
        case (active_msg_type)
            MSG_ADD:     current_msg_len = ADD_LEN;
            MSG_CANCEL:  current_msg_len = CANCEL_LEN;
            MSG_EXECUTE: current_msg_len = EXECUTE_LEN;
            default:     current_msg_len = '0;
        endcase
    end

    // Update for byte_cnt
    logic [8:0]  byte_cnt_next;
    assign byte_cnt_next = total_bytes - {1'b0, current_msg_len};

    // ------------------------------------------------------------------------
    // Error Handling
    // ------------------------------------------------------------------------
    logic framing_error_now;
    assign framing_error_now = s_axis_tvalid && s_axis_tready && s_axis_tlast 
                                && (total_bytes < {1'b0, current_msg_len});

    // ------------------------------------------------------------------------
    // Sequential Process
    // ------------------------------------------------------------------------
    always_ff @(posedge clk or negedge rst_n) begin
        if (!rst_n) begin
            byte_cnt      <= '0;
            prev_tdata    <= '0;
            msg_start     <= '0;
            header_valid  <= '0;
            msg_done      <= '0;
            framing_error <= '0;
            order_event   <= '0;
        end else begin
            msg_start     <= '0;
            header_valid  <= '0;
            msg_done      <= '0;
            framing_error <= '0;
            if (msg_done) order_event <= '0;

            if (s_axis_tvalid && s_axis_tready) begin
                prev_tdata <= s_axis_tdata;

                // ------------------------------------------------------------
                // 1. Start pulse on first byte of new message
                // ------------------------------------------------------------
                if (byte_cnt == 0 && total_bytes >= 1)
                    msg_start <= 1'b1;

                // ------------------------------------------------------------
                // 2. Field extraction from sliding window
                //    Formula: window[((offset - byte_cnt + 8) * 8) +: width]
                //    The +8 accounts for prev_tdata occupying window[63:0];
                //    s_axis_tdata occupies window[127:64], so byte 0 of the
                //    current incoming word is window[64 +: 8] = tdata[7:0].
                // ------------------------------------------------------------

                // msg_type (offset 0, 8 bits)
                if (byte_cnt < 1 && total_bytes >= 1)
                    order_event.msg_type <= msg_type_e'(window[((0 - byte_cnt + 8) * 8) +: 8]);

                // stock_locate (offset 1, 16 bits)
                if (byte_cnt < 3 && total_bytes >= 3)
                    order_event.stock_locate <= bswap16(window[((1 - byte_cnt + 8) * 8) +: 16]);

                // tracking_number (offset 3, 16 bits)
                if (byte_cnt < 5 && total_bytes >= 5)
                    order_event.tracking_number <= bswap16(window[((3 - byte_cnt + 8) * 8) +: 16]);

                // timestamp (offset 5, 48 bits)
                if (byte_cnt < 11 && total_bytes >= 11)
                    order_event.timestamp <= bswap48(window[((5 - byte_cnt + 8) * 8) +: 48]);

                // order_ref (offset 11, 64 bits) — header complete when this lands
                if (byte_cnt < 19 && total_bytes >= 19) begin
                    order_event.order_ref <= bswap64(window[((11 - byte_cnt + 8) * 8) +: 64]);
                    header_valid          <= 1'b1;
                end

                // ------------------------------------------------------------
                // 3. Type-specific payload fields
                // ------------------------------------------------------------
                unique case (active_msg_type)
                    MSG_ADD: begin
                        // side (offset 19, 8 bits) — no swap needed for 1-byte field
                        if (byte_cnt < 20 && total_bytes >= 20)
                            order_event.payload.add.side <= side_e'(window[((19 - byte_cnt + 8) * 8) +: 8]);
                        // shares (offset 20, 32 bits)
                        if (byte_cnt < 24 && total_bytes >= 24)
                            order_event.payload.add.shares <= bswap32(window[((20 - byte_cnt + 8) * 8) +: 32]);
                        // symbol (offset 24, 64 bits) — skipped, not decoded
                        // price (offset 32, 32 bits)
                        if (byte_cnt < 36 && total_bytes >= 36)
                            order_event.payload.add.price <= bswap32(window[((32 - byte_cnt + 8) * 8) +: 32]);
                    end

                    MSG_CANCEL: begin
                        // cancelled_shares (offset 19, 32 bits)
                        if (byte_cnt < 23 && total_bytes >= 23)
                            order_event.payload.cancel.shares <= bswap32(window[((19 - byte_cnt + 8) * 8) +: 32]);
                    end

                    MSG_EXECUTE: begin
                        // executed_shares (offset 19, 32 bits)
                        if (byte_cnt < 23 && total_bytes >= 23)
                            order_event.payload.execute.shares <= bswap32(window[((19 - byte_cnt + 8) * 8) +: 32]);
                        // match_number (offset 23, 64 bits)
                        if (byte_cnt < 31 && total_bytes >= 31)
                            order_event.payload.execute.match <= bswap64(window[((23 - byte_cnt + 8) * 8) +: 64]);
                    end

                    default: ;
                endcase

                // ------------------------------------------------------------
                // 4. Message completion & packet boundary recovery
                // ------------------------------------------------------------
                if (current_msg_len != '0) begin
                    if (total_bytes >= {1'b0, current_msg_len}) begin
                        msg_done <= 1'b1;
                        // If tlast coincides with message boundary, reset cleanly;
                        // otherwise carry leftover bytes into the next cycle
                        byte_cnt <= s_axis_tlast ? '0 : byte_cnt_next[7:0];
                    end else begin
                        if (s_axis_tlast) begin
                            // Packet ended before message was complete — framing error
                            framing_error <= 1'b1;
                            byte_cnt      <= '0;
                        end else begin
                            byte_cnt <= total_bytes;
                        end
                    end
                end else if (!framing_error_now) begin
                    // Unknown message type — pulse done and reset
                    msg_done <= 1'b1;
                    byte_cnt <= '0;
                end
            end
        end
    end

    // ------------------------------------------------------------------------
    // SVA Assertions (formal verification only)
    // ------------------------------------------------------------------------
`ifdef FORMAL
    property p_byte_cnt_bounded;
        @(posedge clk) disable iff (!rst_n)
        (byte_cnt > 0) |-> (byte_cnt < current_msg_len);
    endproperty
    assert property (p_byte_cnt_bounded) else $error("byte_cnt exceeded valid message length");

    property p_msg_done_one_cycle;
        @(posedge clk) disable iff (!rst_n)
        msg_done |=> !msg_done;
    endproperty
    assert property (p_msg_done_one_cycle) else $error("msg_done held high 2+ cycles");

    property p_cnt_resets_after_done;
        @(posedge clk) disable iff (!rst_n)
        (msg_done && s_axis_tlast) |=> (byte_cnt == 0);
    endproperty
    assert property (p_cnt_resets_after_done) else $error("byte_cnt did not reset after msg_done+tlast");

    property p_legal_msg_type;
        @(posedge clk) disable iff (!rst_n)
        (byte_cnt > 0) |-> (order_event.msg_type == MSG_ADD ||
                            order_event.msg_type == MSG_CANCEL ||
                            order_event.msg_type == MSG_EXECUTE);
    endproperty
    assert property (p_legal_msg_type) else $error("illegal msg_type mid-message");
`endif

endmodule

msg_decoder_rand_tb.sv
/* verilator lint_off IMPORTSTAR */
import itch_lite_pkg::*;
/* verilator lint_on IMPORTSTAR */

module msg_decoder_rand_tb;

    timeunit 1ns; timeprecision 1ps;

    // Clock and reset
    logic clk = 0;
    always #5 clk = ~clk;   // 10ns period = 100MHz

    logic rst_n;

    // DUT AXI-Stream Slave interface
    logic [63:0] s_axis_tdata;
    logic        s_axis_tvalid;
    logic [7:0]  s_axis_tkeep;
    logic        s_axis_tlast;
    logic        s_axis_tready;

    // DUT Control & Status interface
    logic        m_axis_tready;
    logic        msg_start;
    logic        header_valid;
    logic        msg_done;
    logic        framing_error;
    logic [287:0] order_event_raw;

    // Unpack raw 288-bit vector to structured type for clean checking
    order_event_t order_event;
    assign order_event = order_event_t'(order_event_raw);

    msg_decoder dut (.*);

    // Waveform dump
    initial begin
        $dumpfile("dump_rand.vcd");
        $dumpvars(0, msg_decoder_rand_tb);
    end

    // ---------------------------------------------------------------------
    // MODULE-SCOPE QUEUE (Bypasses Icarus Verilog automatic argument bug)
    // ---------------------------------------------------------------------
    logic [7:0] tx_queue[$];

    // ---------------------------------------------------------------------
    // 64-Bit AXI-Stream Driver Task (Consumes tx_queue directly)
    // ---------------------------------------------------------------------
    task automatic send_message(input logic set_tlast = 1'b1);
        while (tx_queue.size() > 0) begin
            logic [63:0] word_data = '0;
            logic [7:0]  word_keep = '0;
            int n = (tx_queue.size() >= 8) ? 8 : tx_queue.size();

            // Pack up to 8 bytes into little-endian AXI-Stream byte lanes
            for (int i = 0; i < n; i++) begin
                word_data[i*8 +: 8] = tx_queue.pop_front();
                word_keep[i]        = 1'b1;
            end

            s_axis_tdata  <= word_data;
            s_axis_tkeep  <= word_keep;
            s_axis_tvalid <= 1'b1;
            s_axis_tlast  <= (tx_queue.size() == 0 && set_tlast) ? 1'b1 : 1'b0;

            // Wait for handshake on rising clock edge
            do begin
                @(posedge clk);
            end while (!s_axis_tready);
        end

        // Deassert bus after all words are accepted
        s_axis_tvalid <= 1'b0;
        s_axis_tlast  <= 1'b0;
        s_axis_tkeep  <= '0;
        s_axis_tdata  <= '0;
    endtask

    // ---------------------------------------------------------------------
    // Synchronization Task: Wait for NBA settling, then check completion
    // ---------------------------------------------------------------------
    int errors = 0;
    task automatic wait_and_check_done();
        #1; // Step past NBA region to prevent delta-cycle sampling races
        
        if (!msg_done) begin
            int timeout = 20;
            while (!msg_done && timeout > 0) begin
                @(posedge clk);
                #1;
                timeout--;
            end
        end

        if (!msg_done) begin
            $display("FAIL: msg_done did not pulse within timeout!");
            errors++;
        end
    endtask

    // ---------------------------------------------------------------------
    // Value Checker Task
    // ---------------------------------------------------------------------
    task automatic check(string name, logic [63:0] actual, logic [63:0] expected);
        if (actual !== expected) begin
            $display("FAIL: %s = %0d, expected %0d", name, actual, expected);
            errors++;
        end
    endtask

    // ---------------------------------------------------------------------
    // Random Message Generator & Checker
    // ---------------------------------------------------------------------
    task automatic gen_and_check();
        int kind = $urandom_range(0, 2);
        logic [15:0] r_locate = $urandom_range(0, 65535);
        logic [15:0] r_track  = $urandom_range(0, 65535);
        logic [47:0] r_ts     = {$urandom, $urandom} & 48'hFFFF_FFFF_FFFF;
        logic [63:0] r_ref    = {$urandom, $urandom};
        logic [31:0] r_shares = $urandom_range(1, 100000);
        logic [31:0] r_price  = $urandom_range(1, 2000000);
        logic [63:0] r_match  = {$urandom, $urandom};

        // Populate the shared module-level queue
        tx_queue = {};
        tx_queue.push_back(kind == 0 ? MSG_ADD : kind == 1 ? MSG_CANCEL : MSG_EXECUTE);
        tx_queue.push_back(r_locate[15:8]); tx_queue.push_back(r_locate[7:0]);
        tx_queue.push_back(r_track[15:8]);  tx_queue.push_back(r_track[7:0]);
        for (int i = 5; i >= 0; i--) tx_queue.push_back(r_ts[i*8 +: 8]);
        for (int i = 7; i >= 0; i--) tx_queue.push_back(r_ref[i*8 +: 8]);

        if (kind == 0) begin // Add
            tx_queue.push_back(SIDE_BUY);
            for (int i = 3; i >= 0; i--) tx_queue.push_back(r_shares[i*8 +: 8]);
            for (int i = 0; i < 8; i++)  tx_queue.push_back(8'h20); // symbol (skipped by DUT)
            for (int i = 3; i >= 0; i--) tx_queue.push_back(r_price[i*8 +: 8]);
        end else if (kind == 1) begin // Cancel
            for (int i = 3; i >= 0; i--) tx_queue.push_back(r_shares[i*8 +: 8]);
        end else begin // Execute
            for (int i = 3; i >= 0; i--) tx_queue.push_back(r_shares[i*8 +: 8]);
            for (int i = 7; i >= 0; i--) tx_queue.push_back(r_match[i*8 +: 8]);
        end

        // Stream over 64-bit AXI-Stream and wait for completion
        send_message(1'b1);
        wait_and_check_done();

        // Check decoded fields on the active, settled msg_done cycle
        check("stock_locate",    order_event.stock_locate,    r_locate);
        check("tracking_number", order_event.tracking_number, r_track);
        check("timestamp",       order_event.timestamp,       r_ts);
        check("order_ref",       order_event.order_ref,       r_ref);
        
        if (kind == 0) begin
            check("side",   order_event.payload.add.side,   SIDE_BUY);
            check("shares", order_event.payload.add.shares, r_shares);
            check("price",  order_event.payload.add.price,  r_price);
        end else if (kind == 1) begin
            check("cancelled_shares", order_event.payload.cancel.shares, r_shares);
        end else begin
            check("executed_shares", order_event.payload.execute.shares, r_shares);
            check("match_number",    order_event.payload.execute.match,  r_match);
        end
        
        @(posedge clk);
    endtask

    // ---------------------------------------------------------------------
    // Test Sequence
    // ---------------------------------------------------------------------
    initial begin
        rst_n         <= 0;
        s_axis_tvalid <= 0;
        s_axis_tdata  <= '0;
        s_axis_tkeep  <= '0;
        s_axis_tlast  <= 0;
        m_axis_tready <= 1; // Downstream consumer always ready

        repeat (3) @(posedge clk);
        rst_n <= 1;
        @(posedge clk);

        repeat (200) gen_and_check(); // Run 200 randomized messages

        if (errors == 0) $display("=== ALL %0d RANDOM TESTS PASSED ===", 200);
        else             $display("=== %0d CHECK(S) FAILED ===", errors);
        $finish;
    end

endmodule

dump_rand.vcd
$date
	Sun Jul 26 18:24:49 2026
$end
$version
	Icarus Verilog
$end
$timescale
	1ps
$end
$scope module msg_decoder_rand_tb $end
$var wire 288 ! order_event [287:0] $end
$var wire 1 " s_axis_tready $end
$var wire 288 # order_event_raw [287:0] $end
$var wire 1 $ msg_start $end
$var wire 1 % msg_done $end
$var wire 1 & header_valid $end
$var wire 1 ' framing_error $end
$var reg 1 ( clk $end
$var reg 1 ) m_axis_tready $end
$var reg 1 * rst_n $end
$var reg 64 + s_axis_tdata [63:0] $end
$var reg 8 , s_axis_tkeep [7:0] $end
$var reg 1 - s_axis_tlast $end
$var reg 1 . s_axis_tvalid $end
$var integer 32 / errors [31:0] $end
$scope module dut $end
$var wire 1 ( clk $end
$var wire 1 0 framing_error_now $end
$var wire 1 ) m_axis_tready $end
$var wire 288 1 order_event_raw [287:0] $end
$var wire 1 * rst_n $end
$var wire 64 2 s_axis_tdata [63:0] $end
$var wire 8 3 s_axis_tkeep [7:0] $end
$var wire 1 - s_axis_tlast $end
$var wire 1 " s_axis_tready $end
$var wire 1 . s_axis_tvalid $end
$var wire 128 4 window [127:0] $end
$var wire 9 5 total_bytes [8:0] $end
$var wire 4 6 bytes_in_word [3:0] $end
$var wire 9 7 byte_cnt_next [8:0] $end
$var reg 8 8 active_msg_type [7:0] $end
$var reg 8 9 byte_cnt [7:0] $end
$var reg 8 : current_msg_len [7:0] $end
$var reg 1 ' framing_error $end
$var reg 1 & header_valid $end
$var reg 1 % msg_done $end
$var reg 1 $ msg_start $end
$var reg 288 ; order_event [287:0] $end
$var reg 64 < prev_tdata [63:0] $end
$upscope $end
$scope task check $end
$upscope $end
$scope task gen_and_check $end
$scope begin $ivl_for_loop1 $end
$upscope $end
$scope begin $ivl_for_loop2 $end
$upscope $end
$scope begin $ivl_for_loop3 $end
$upscope $end
$scope begin $ivl_for_loop4 $end
$upscope $end
$scope begin $ivl_for_loop5 $end
$upscope $end
$scope begin $ivl_for_loop6 $end
$upscope $end
$scope begin $ivl_for_loop7 $end
$upscope $end
$scope begin $ivl_for_loop8 $end
$upscope $end
$upscope $end
$scope task send_message $end
$scope begin $unm_blk_18 $end
$scope begin $ivl_for_loop0 $end
$upscope $end
$upscope $end
$upscope $end
$scope task wait_and_check_done $end
$scope begin $unm_blk_21 $end
$upscope $end
$upscope $end
$upscope $end
$enddefinitions $end
$comment Show the parameter values. $end
$dumpall
$end
#0
$dumpvars
b0 <
b0 ;
b0 :
b0 9
b0 8
b0 7
b0 6
b0 5
b0 4
b0 3
b0 2
b0 1
00
b0 /
0.
0-
b0 ,
b0 +
0*
1)
0(
0'
0&
0%
0$
b0 #
0"
b0 !
$end
#5000
1(
#10000
0(
#15000
1(
#20000
0(
#25000
1"
1*
1(
#30000
0(
#35000
b10111 :
b1011000 8
b111110001 7
b1000 5
b1000 6
b10000110011000110101011010000100000001001000100101000000010110000000000000000000000000000000000000000000000000000000000000000000 4
1.
b11111111 ,
b11111111 3
b1000011001100011010101101000010000000100100010010100000001011000 +
b1000011001100011010101101000010000000100100010010100000001011000 2
1(
#40000
0(
#45000
b111111001 7
b10000 5
b110010100011011001100111011111110001100000110101111011101110011000011001100011010101101000010000000100100010010100000001011000 4
b1000 9
b10110000100000010001001000001001000010000000000000000000000000000000000000000000000000000000000000000000000000000000000000000000000000000000000000000000000000000000000000000000000000000000000000000000000000000000000000000000000000000000000000000000000000000000000000000000000000000000000 !
b10110000100000010001001000001001000010000000000000000000000000000000000000000000000000000000000000000000000000000000000000000000000000000000000000000000000000000000000000000000000000000000000000000000000000000000000000000000000000000000000000000000000000000000000000000000000000000000000 #
b10110000100000010001001000001001000010000000000000000000000000000000000000000000000000000000000000000000000000000000000000000000000000000000000000000000000000000000000000000000000000000000000000000000000000000000000000000000000000000000000000000000000000000000000000000000000000000000000 1
b10110000100000010001001000001001000010000000000000000000000000000000000000000000000000000000000000000000000000000000000000000000000000000000000000000000000000000000000000000000000000000000000000000000000000000000000000000000000000000000000000000000000000000000000000000000000000000000000 ;
1$
b1000011001100011010101101000010000000100100010010100000001011000 <
b11001010001101100110011101111111000110000011010111101110111001 +
b11001010001101100110011101111111000110000011010111101110111001 2
1(
#50000
0(
#55000
b111 6
b0 7
b10111 5
b100010000111000000000000000000110010110000100110000100011001010001101100110011101111111000110000011010111101110111001 4
b10000 9
b10110000100000010001001000001001000010001010110011000111000011010111001011110110000110100000000000000000000000000000000000000000000000000000000000000000000000000000000000000000000000000000000000000000000000000000000000000000000000000000000000000000000000000000000000000000000000000000000 !
b10110000100000010001001000001001000010001010110011000111000011010111001011110110000110100000000000000000000000000000000000000000000000000000000000000000000000000000000000000000000000000000000000000000000000000000000000000000000000000000000000000000000000000000000000000000000000000000000 #
b10110000100000010001001000001001000010001010110011000111000011010111001011110110000110100000000000000000000000000000000000000000000000000000000000000000000000000000000000000000000000000000000000000000000000000000000000000000000000000000000000000000000000000000000000000000000000000000000 1
b10110000100000010001001000001001000010001010110011000111000011010111001011110110000110100000000000000000000000000000000000000000000000000000000000000000000000000000000000000000000000000000000000000000000000000000000000000000000000000000000000000000000000000000000000000000000000000000000 ;
b11001010001101100110011101111111000110000011010111101110111001 <
0$
1-
b1111111 ,
b1111111 3
b10001000011100000000000000000011001011000010011000010 +
b10001000011100000000000000000011001011000010011000010 2
1(
#60000
0(
#65000
b10111 :
b0 6
b111101001 7
b0 5
b1011000 8
b10001000011100000000000000000011001011000010011000010 4
b0 9
1%
1&
b10110000100000010001001000001001000010001010110011000111000011010111001011110110000110111000110110111111001100110001101001100101100001010000100011001010000000000000000000011100001000100000000000000000000000000000000000000000000000000000000000000000000000000000000000000000000000000000000 !
b10110000100000010001001000001001000010001010110011000111000011010111001011110110000110111000110110111111001100110001101001100101100001010000100011001010000000000000000000011100001000100000000000000000000000000000000000000000000000000000000000000000000000000000000000000000000000000000000 #
b10110000100000010001001000001001000010001010110011000111000011010111001011110110000110111000110110111111001100110001101001100101100001010000100011001010000000000000000000011100001000100000000000000000000000000000000000000000000000000000000000000000000000000000000000000000000000000000000 1
b10110000100000010001001000001001000010001010110011000111000011010111001011110110000110111000110110111111001100110001101001100101100001010000100011001010000000000000000000011100001000100000000000000000000000000000000000000000000000000000000000000000000000000000000000000000000000000000000 ;
b10001000011100000000000000000011001011000010011000010 <
b0 +
b0 2
b0 ,
b0 3
0-
0.
1(
#70000
0(
#75000
b111110001 7
b1000 5
b10111 :
b1000 6
b1011000 8
b1100011111110011110100100101101110001101101010011110110010110000000000000010001000011100000000000000000011001011000010011000010 4
b0 !
b0 #
b0 1
b0 ;
0%
0&
1.
b11111111 ,
b11111111 3
b110001111111001111010010010110111000110110101001111011001011000 +
b110001111111001111010010010110111000110110101001111011001011000 2
1(
#80000
0(
#85000
b111111001 7
b10000 5
b1010101110001011000010011110111011000101100011000100100001101110110001111111001111010010010110111000110110101001111011001011000 4
b1000 9
b10110001111011011010100110001100010110100000000000000000000000000000000000000000000000000000000000000000000000000000000000000000000000000000000000000000000000000000000000000000000000000000000000000000000000000000000000000000000000000000000000000000000000000000000000000000000000000000000 !
b10110001111011011010100110001100010110100000000000000000000000000000000000000000000000000000000000000000000000000000000000000000000000000000000000000000000000000000000000000000000000000000000000000000000000000000000000000000000000000000000000000000000000000000000000000000000000000000000 #
b10110001111011011010100110001100010110100000000000000000000000000000000000000000000000000000000000000000000000000000000000000000000000000000000000000000000000000000000000000000000000000000000000000000000000000000000000000000000000000000000000000000000000000000000000000000000000000000000 1
b10110001111011011010100110001100010110100000000000000000000000000000000000000000000000000000000000000000000000000000000000000000000000000000000000000000000000000000000000000000000000000000000000000000000000000000000000000000000000000000000000000000000000000000000000000000000000000000000 ;
1$
b110001111111001111010010010110111000110110101001111011001011000 <
b101010111000101100001001111011101100010110001100010010000110111 +
b101010111000101100001001111011101100010110001100010010000110111 2
1(
#90000
0(
#95000
b111 6
b0 7
b10111 5
b10100000111001000000001000000001010101011010010000100110101010111000101100001001111011101100010110001100010010000110111 4
b10000 9
b10110001111011011010100110001100010110111101001111110010110001100110111001001001100011000000000000000000000000000000000000000000000000000000000000000000000000000000000000000000000000000000000000000000000000000000000000000000000000000000000000000000000000000000000000000000000000000000000 !
b10110001111011011010100110001100010110111101001111110010110001100110111001001001100011000000000000000000000000000000000000000000000000000000000000000000000000000000000000000000000000000000000000000000000000000000000000000000000000000000000000000000000000000000000000000000000000000000000 #
b10110001111011011010100110001100010110111101001111110010110001100110111001001001100011000000000000000000000000000000000000000000000000000000000000000000000000000000000000000000000000000000000000000000000000000000000000000000000000000000000000000000000000000000000000000000000000000000000 1
b10110001111011011010100110001100010110111101001111110010110001100110111001001001100011000000000000000000000000000000000000000000000000000000000000000000000000000000000000000000000000000000000000000000000000000000000000000000000000000000000000000000000000000000000000000000000000000000000 ;
b101010111000101100001001111011101100010110001100010010000110111 <
0$
1-
b1111111 ,
b1111111 3
b1010000011100100000000100000000101010101101001000010011 +
b1010000011100100000000100000000101010101101001000010011 2
1(
#100000
0(
#105000
b10111 :
b0 6
b111101001 7
b0 5
b1011000 8
b1010000011100100000000100000000101010101101001000010011 4
b0 9
1%
1&
b10110001111011011010100110001100010110111101001111110010110001100110111001001001100011001100010111101111000010011000101010101010001001111010010101010100000000000000001011100100101000000000000000000000000000000000000000000000000000000000000000000000000000000000000000000000000000000000000 !
b10110001111011011010100110001100010110111101001111110010110001100110111001001001100011001100010111101111000010011000101010101010001001111010010101010100000000000000001011100100101000000000000000000000000000000000000000000000000000000000000000000000000000000000000000000000000000000000000 #
b10110001111011011010100110001100010110111101001111110010110001100110111001001001100011001100010111101111000010011000101010101010001001111010010101010100000000000000001011100100101000000000000000000000000000000000000000000000000000000000000000000000000000000000000000000000000000000000000 1
b10110001111011011010100110001100010110111101001111110010110001100110111001001001100011001100010111101111000010011000101010101010001001111010010101010100000000000000001011100100101000000000000000000000000000000000000000000000000000000000000000000000000000000000000000000000000000000000000 ;
b1010000011100100000000100000000101010101101001000010011 <
b0 +
b0 2
b0 ,
b0 3
0-
0.
1(
#110000
0(
#115000
b111101001 7
b1000 5
b11111 :
b1000 6
b1000101 8
b10101110110001010100111000000000011101000111011001100111010001010000000001010000011100100000000100000000101010101101001000010011 4
b0 !
b0 #
b0 1
b0 ;
0%
0&
1.
b11111111 ,
b11111111 3
b1010111011000101010011100000000001110100011101100110011101000101 +
b1010111011000101010011100000000001110100011101100110011101000101 2
1(
#120000
0(
#125000
b111110001 7
b10000 5
b10110101111010010100010001110010111100101110001001001010110001010111011000101010011100000000001110100011101100110011101000101 4
b1000 9
b10001010110011101110110011101000000000000000000000000000000000000000000000000000000000000000000000000000000000000000000000000000000000000000000000000000000000000000000000000000000000000000000000000000000000000000000000000000000000000000000000000000000000000000000000000000000000000000000 !
b10001010110011101110110011101000000000000000000000000000000000000000000000000000000000000000000000000000000000000000000000000000000000000000000000000000000000000000000000000000000000000000000000000000000000000000000000000000000000000000000000000000000000000000000000000000000000000000000 #
b10001010110011101110110011101000000000000000000000000000000000000000000000000000000000000000000000000000000000000000000000000000000000000000000000000000000000000000000000000000000000000000000000000000000000000000000000000000000000000000000000000000000000000000000000000000000000000000000 1
b10001010110011101110110011101000000000000000000000000000000000000000000000000000000000000000000000000000000000000000000000000000000000000000000000000000000000000000000000000000000000000000000000000000000000000000000000000000000000000000000000000000000000000000000000000000000000000000000 ;
1$
b1010111011000101010011100000000001110100011101100110011101000101 <
b1011010111101001010001000111001011110010111000100100101011000 +
b1011010111101001010001000111001011110010111000100100101011000 2
1(
#130000
0(
#135000
b111111001 7
b11000 5
b10000101010010110100110100000000000000000010110101011000101010110001011010111101001010001000111001011110010111000100100101011000 4
b10000 9
b10001010110011101110110011101000000000001001110110001011010111001011000010010010101110000000000000000000000000000000000000000000000000000000000000000000000000000000000000000000000000000000000000000000000000000000000000000000000000000000000000000000000000000000000000000000000000000000000 !
b10001010110011101110110011101000000000001001110110001011010111001011000010010010101110000000000000000000000000000000000000000000000000000000000000000000000000000000000000000000000000000000000000000000000000000000000000000000000000000000000000000000000000000000000000000000000000000000000 #
b10001010110011101110110011101000000000001001110110001011010111001011000010010010101110000000000000000000000000000000000000000000000000000000000000000000000000000000000000000000000000000000000000000000000000000000000000000000000000000000000000000000000000000000000000000000000000000000000 1
b10001010110011101110110011101000000000001001110110001011010111001011000010010010101110000000000000000000000000000000000000000000000000000000000000000000000000000000000000000000000000000000000000000000000000000000000000000000000000000000000000000000000000000000000000000000000000000000000 ;
b1011010111101001010001000111001011110010111000100100101011000 <
0$
b1000010101001011010011010000000000000000001011010101100010101011 +
b1000010101001011010011010000000000000000001011010101100010101011 2
1(
#140000
0(
#145000
b111 6
b0 7
b11111 5
b100000000010001000111011010000000000101010000111011100111000010101001011010011010000000000000000001011010101100010101011 4
b11000 9
1&
b10001010110011101110110011101000000000001001110110001011010111001011000010010010101110001011110100011100010100010111101000101101010101101011000001011010000000000000000010011010100101100000000000000000000000000000000000000000000000000000000000000000000000000000000000000000000000000000000 !
b10001010110011101110110011101000000000001001110110001011010111001011000010010010101110001011110100011100010100010111101000101101010101101011000001011010000000000000000010011010100101100000000000000000000000000000000000000000000000000000000000000000000000000000000000000000000000000000000 #
b10001010110011101110110011101000000000001001110110001011010111001011000010010010101110001011110100011100010100010111101000101101010101101011000001011010000000000000000010011010100101100000000000000000000000000000000000000000000000000000000000000000000000000000000000000000000000000000000 1
b10001010110011101110110011101000000000001001110110001011010111001011000010010010101110001011110100011100010100010111101000101101010101101011000001011010000000000000000010011010100101100000000000000000000000000000000000000000000000000000000000000000000000000000000000000000000000000000000 ;
b1000010101001011010011010000000000000000001011010101100010101011 <
1-
b1111111 ,
b1111111 3
b10000000001000100011101101000000000010101000011101110011 +
b10000000001000100011101101000000000010101000011101110011 2
1(
#150000
0(
#155000
b11111 :
b0 6
b111100001 7
b0 5
b1000101 8
b10000000001000100011101101000000000010101000011101110011 4
b0 9
1%
b10001010110011101110110011101000000000001001110110001011010111001011000010010010101110001011110100011100010100010111101000101101010101101011000001011010000000000000000010011010100101110000101011100111000011100001010010000000011101100100010100000000000000000000000000000000000000000000000 !
b10001010110011101110110011101000000000001001110110001011010111001011000010010010101110001011110100011100010100010111101000101101010101101011000001011010000000000000000010011010100101110000101011100111000011100001010010000000011101100100010100000000000000000000000000000000000000000000000 #
b10001010110011101110110011101000000000001001110110001011010111001011000010010010101110001011110100011100010100010111101000101101010101101011000001011010000000000000000010011010100101110000101011100111000011100001010010000000011101100100010100000000000000000000000000000000000000000000000 1
b10001010110011101110110011101000000000001001110110001011010111001011000010010010101110001011110100011100010100010111101000101101010101101011000001011010000000000000000010011010100101110000101011100111000011100001010010000000011101100100010100000000000000000000000000000000000000000000000 ;
b10000000001000100011101101000000000010101000011101110011 <
0&
b0 +
b0 2
b0 ,
b0 3
0-
0.
1(
#160000
0(
#165000
b111110001 7
b1000 5
b10111 :
b1000 6
b1011000 8
b1001100101100011111011001100010011100111100011010101010110000000000010000000001000100011101101000000000010101000011101110011 4
b0 !
b0 #
b0 1
b0 ;
0%
1.
b11111111 ,
b11111111 3
b100110010110001111101100110001001110011110001101010101011000 +
b100110010110001111101100110001001110011110001101010101011000 2
1(
#170000
0(
